Metadata-Version: 2.1
Name: caffeinate
Version: 0.0.4
Summary: Don't let your computer go to sleep while you're busy thinking
Home-page: https://github.com/subash774/Caffeinate
Author: Subash Poudyal
Author-email: subash.poudyal8@gmail.com
License: MIT
Platform: UNKNOWN
Requires-Python: >=3.6.3
